__init__.py
simple_lexical_search.py
simple_vector_store.py
simple_vector_store-0.0.3.dist-info/licenses/LICENSE
simple_vector_store-0.0.3.dist-info/METADATA
simple_vector_store-0.0.3.dist-info/WHEEL
simple_vector_store-0.0.3.dist-info/top_level.txt
simple_vector_store-0.0.3.dist-info/RECORD
