Metadata-Version: 2.4
Name: simple-vector-store
Version: 0.0.3
Summary: A pure python vector store with hybrid search and metadata filtering.
Author-email: Pat Wendorf <dungeons@gmail.com>
Project-URL: Homepage, https://github.com/patw/SimpleVectorStore
Project-URL: Bug Tracker, https://github.com/patw/SimpleVectorStore/issues
Keywords: vector store,search,semantic search,lexical search,hybrid search
Classifier: Programming Language :: Python :: 3
Classifier: License :: OSI Approved :: MIT License
Classifier: Operating System :: OS Independent
Classifier: Intended Audience :: Developers
Classifier: Topic :: Scientific/Engineering :: Artificial Intelligence
Classifier: Topic :: Software Development :: Libraries :: Python Modules
Requires-Python: >=3.8
License-File: LICENSE
Requires-Dist: numpy>=1.20.0
Dynamic: license-file
